xkits_logger/__init__.py
xkits_logger/attribute.py
xkits_logger/colorful.py
xkits_logger/logger.py
xkits_logger-0.2.dist-info/LICENSE
xkits_logger-0.2.dist-info/METADATA
xkits_logger-0.2.dist-info/WHEEL
xkits_logger-0.2.dist-info/top_level.txt
xkits_logger-0.2.dist-info/zip-safe
xkits_logger-0.2.dist-info/RECORD
