Metadata-Version: 2.1
Name: xkits-logger
Version: 0.2
Summary: Logging module
Home-page: https://github.com/bondbox/xlogger/
Author: Mingzhe Zou
Author-email: zoumingzhe@outlook.com
License: GPLv2
Project-URL: Source Code, https://github.com/bondbox/xlogger/
Project-URL: Bug Tracker, https://github.com/bondbox/xlogger/issues
Project-URL: Documentation, https://github.com/bondbox/xlogger/
Keywords: colorama,colorlog,logger,logging
Platform: any
Classifier: Programming Language :: Python
Classifier: Programming Language :: Python :: 3
Requires-Python: >=3.8
License-File: LICENSE
Requires-Dist: colorama
Requires-Dist: colorlog
